vresto/__init__.py
vresto/_version.py
vresto/api/README.md
vresto/api/__init__.py
vresto/api/auth.py
vresto/api/catalog.py
vresto/api/config.py
vresto/api/env_loader.py
vresto/api/product_level_config.py
vresto/api/stac_mappings.py
vresto/bands/__init__.py
vresto/bands/band_io.py
vresto/bands/band_utils.py
vresto/bands/composer.py
vresto/cli/__init__.py
vresto/cli/main.py
vresto/products/__init__.py
vresto/products/downloader.py
vresto/products/product_name.py
vresto/products/products_manager.py
vresto/services/tiles.py
vresto/ui/__init__.py
vresto/ui/app.py
vresto/ui/map_interface.py
vresto/ui/visualization/__init__.py
vresto/ui/visualization/helpers.py
vresto/ui/widgets/README.md
vresto/ui/widgets/activity_log.py
vresto/ui/widgets/credentials_menu.py
vresto/ui/widgets/date_picker.py
vresto/ui/widgets/download_tab.py
vresto/ui/widgets/hi_res_tiler_tab.py
vresto/ui/widgets/map_search_tab.py
vresto/ui/widgets/map_widget.py
vresto/ui/widgets/name_search_tab.py
vresto/ui/widgets/product_analysis_tab.py
vresto/ui/widgets/product_viewer.py
vresto/ui/widgets/search_results_panel.py
vresto-0.2.3.dist-info/METADATA
vresto-0.2.3.dist-info/WHEEL
vresto-0.2.3.dist-info/entry_points.txt
vresto-0.2.3.dist-info/licenses/LICENSE.txt
vresto-0.2.3.dist-info/RECORD
