Metadata-Version: 2.4
Name: vresto
Version: 0.2.3
Summary: satellite product browser
License-File: LICENSE.txt
Requires-Python: >=3.11
Requires-Dist: boto3>=1.35.0
Requires-Dist: ipython>=9.2.0
Requires-Dist: localtileserver>=0.10.0
Requires-Dist: loguru>=0.7.3
Requires-Dist: matplotlib>=3.10.7
Requires-Dist: nicegui>=2.16.1
Requires-Dist: pillow>=12.0.0
Requires-Dist: plotly>=6.5.0
Requires-Dist: pre-commit>=4.2.0
Requires-Dist: psutil>=7.0.0
Requires-Dist: pycql2>=0.2.0
Requires-Dist: pystac-client>=0.8.6
Requires-Dist: pytest-xdist>=3.2.0
Requires-Dist: pytest>=8.3.5
Requires-Dist: python-dateutil>=2.9.0
Requires-Dist: python-dotenv>=1.0.0
Requires-Dist: rasterio>=1.4.3
Requires-Dist: requests>=2.31.0
Requires-Dist: rich>=13.0.0
Requires-Dist: twine>=6.1.0
Requires-Dist: typer>=0.12.0
Provides-Extra: dev
Requires-Dist: moto>=4.0.0; extra == 'dev'
Requires-Dist: numpy>=1.26.0; extra == 'dev'
Requires-Dist: rasterio>=1.4.0; extra == 'dev'
Requires-Dist: ruff>=0.1.0; extra == 'dev'
Provides-Extra: docs
Requires-Dist: loguru>=0.7.3; extra == 'docs'
Requires-Dist: mkdocs-htmlproofer-plugin>=1.2.1; extra == 'docs'
Requires-Dist: mkdocs-include-markdown-plugin>=6.0.0; extra == 'docs'
Requires-Dist: mkdocs-material>=9.0.0; extra == 'docs'
Requires-Dist: mkdocs>=1.5.0; extra == 'docs'
Requires-Dist: pymdown-extensions>=9.0.0; extra == 'docs'
